{
  "assets": [
    {
      "author": "",
      "author_url": null,
      "download_url": "https://images.metmuseum.org/CRDImages/md/original/DT119.jpg",
      "height": null,
      "id": "472562",
      "license": "CC0",
      "media_type": "image",
      "preview_url": "https://images.metmuseum.org/CRDImages/md/web-large/DT119.jpg",
      "provider": "met",
      "source_url": "https://www.metmuseum.org/art/collection/search/472562",
      "tags": [
        "Christ",
        "Virgin Mary",
        "Crucifixion",
        "Saints"
      ],
      "title": "The Fieschi Morgan Staurotheke",
      "width": null
    },
    {
      "author": "Northern Highlands artist",
      "author_url": null,
      "download_url": "https://images.metmuseum.org/CRDImages/ao/original/DP100984.jpg",
      "height": null,
      "id": "317877",
      "license": "CC0",
      "media_type": "image",
      "preview_url": "https://images.metmuseum.org/CRDImages/ao/web-large/DP100984.jpg",
      "provider": "met",
      "source_url": "https://www.metmuseum.org/art/collection/search/317877",
      "tags": [],
      "title": "Processional Cross",
      "width": null
    },
    {
      "author": "Joachim Patinir",
      "author_url": null,
      "download_url": "https://images.metmuseum.org/CRDImages/ep/original/DT5549.jpg",
      "height": null,
      "id": "437261",
      "license": "CC0",
      "media_type": "image",
      "preview_url": "https://images.metmuseum.org/CRDImages/ep/web-large/DT5549.jpg",
      "provider": "met",
      "source_url": "https://www.metmuseum.org/art/collection/search/437261",
      "tags": [
        "Landscapes",
        "Saint Jerome",
        "Saint John the Baptist",
        "Jesus",
        "Baptism of Christ"
      ],
      "title": "The Penitence of Saint Jerome",
      "width": null
    },
    {
      "author": "Frederic Edwin Church (American, 1826–1900)",
      "author_url": null,
      "download_url": "https://openaccess-cdn.clevelandart.org/1976.30/1976.30_web.jpg",
      "height": 823,
      "id": "148774",
      "license": "CC0",
      "media_type": "image",
      "preview_url": "https://openaccess-cdn.clevelandart.org/1976.30/1976.30_web.jpg",
      "provider": "cleveland",
      "source_url": "https://clevelandart.org/art/1976.30",
      "tags": [],
      "title": "Niagara Falls by Moonlight",
      "width": 1263
    },
    {
      "author": "Paul Cezanne (French, 1839–1906)",
      "author_url": null,
      "download_url": "https://openaccess-cdn.clevelandart.org/1936.19/1936.19_web.jpg",
      "height": 723,
      "id": "115405",
      "license": "CC0",
      "media_type": "image",
      "preview_url": "https://openaccess-cdn.clevelandart.org/1936.19/1936.19_web.jpg",
      "provider": "cleveland",
      "source_url": "https://clevelandart.org/art/1936.19",
      "tags": [],
      "title": "The Pigeon Tower at Bellevue",
      "width": 900
    },
    {
      "author": "",
      "author_url": null,
      "download_url": "https://openaccess-cdn.clevelandart.org/2013.341/2013.341_web.jpg",
      "height": 751,
      "id": "170865",
      "license": "CC0",
      "media_type": "image",
      "preview_url": "https://openaccess-cdn.clevelandart.org/2013.341/2013.341_web.jpg",
      "provider": "cleveland",
      "source_url": "https://clevelandart.org/art/2013.341",
      "tags": [],
      "title": "A princess on a terrace with attendants at night (recto); Calligraphy (verso)",
      "width": 900
    },
    {
      "author": "Rico Cilliers, Dario Barresi, Greg Zaal, Jenelle van Heerden",
      "author_url": null,
      "download_url": "https://polyhaven.com/a/moon_dusted_05",
      "height": null,
      "id": "moon_dusted_05",
      "license": "CC0",
      "media_type": "image",
      "preview_url": "https://cdn.polyhaven.com/asset_img/thumbs/moon_dusted_05.png?height=256",
      "provider": "polyhaven",
      "source_url": "https://polyhaven.com/a/moon_dusted_05",
      "tags": [
        "rough",
        "dirt",
        "coarse",
        "exterior",
        "regolith",
        "dusted",
        "extraterrestrial",
        "lunar",
        "space"
      ],
      "title": "Moon Dusted 05",
      "width": null
    },
    {
      "author": "Greg Zaal, Jenelle van Heerden, Dario Barresi, Rico Cilliers",
      "author_url": null,
      "download_url": "https://polyhaven.com/a/moon_footprints_01",
      "height": null,
      "id": "moon_footprints_01",
      "license": "CC0",
      "media_type": "image",
      "preview_url": "https://cdn.polyhaven.com/asset_img/thumbs/moon_footprints_01.png?height=256",
      "provider": "polyhaven",
      "source_url": "https://polyhaven.com/a/moon_footprints_01",
      "tags": [
        "rough",
        "dirt",
        "course",
        "exterior",
        "regolith",
        "dusted",
        "footprints",
        "path",
        "trail",
        "extraterrestrial",
        "space",
        "lunar"
      ],
      "title": "Moon Footprints 01",
      "width": null
    },
    {
      "author": "Rico Cilliers, Greg Zaal, Jenelle van Heerden",
      "author_url": null,
      "download_url": "https://polyhaven.com/a/moon_dusted_02",
      "height": null,
      "id": "moon_dusted_02",
      "license": "CC0",
      "media_type": "image",
      "preview_url": "https://cdn.polyhaven.com/asset_img/thumbs/moon_dusted_02.png?height=256",
      "provider": "polyhaven",
      "source_url": "https://polyhaven.com/a/moon_dusted_02",
      "tags": [
        "rough",
        "dirt",
        "coarse",
        "exterior",
        "regolith",
        "dusted",
        "pebbles",
        "lunar",
        "extraterrestrial",
        "space"
      ],
      "title": "Moon Dusted 02",
      "width": null
    },
    {
      "author": "Chesley Benestell, Chesley Benestell, Chesley Benestell",
      "author_url": null,
      "download_url": "http://www.fondazionemicheletti.eu/contents/documentazione/archivio/Giorgio_e_Gabriella_Nebbia/Arc.Nebbia.Solare.09.051.jpg",
      "height": null,
      "id": "/10902/8F1E98AC37E0182AF020DAEDCE7727671C14FCA0",
      "license": "In Copyright",
      "media_type": "image",
      "preview_url": "https://api.europeana.eu/thumbnail/v2/url.json?uri=http%3A%2F%2Fwww.fondazionemicheletti.eu%2Fcontents%2Fdocumentazione%2Farchivio%2FGiorgio_e_Gabriella_Nebbia%2FArc.Nebbia.Solare.09.051.jpg&type=IMAGE",
      "provider": "europeana",
      "source_url": "https://www.europeana.eu/item/10902/8F1E98AC37E0182AF020DAEDCE7727671C14FCA0?utm_source=api&utm_medium=api&utm_campaign=api2demo",
      "tags": [],
      "title": "Space Pioneers",
      "width": null
    },
    {
      "author": "",
      "author_url": null,
      "download_url": "https://www.filmportal.de/sites/default/files/image/2020-09/fn122205_pic_06.jpg",
      "height": null,
      "id": "/08604/_filmportal_de_node_1668927",
      "license": "In Copyright",
      "media_type": "image",
      "preview_url": "https://api.europeana.eu/thumbnail/v2/url.json?uri=https%3A%2F%2Fwww.filmportal.de%2Fsites%2Fdefault%2Ffiles%2Fimage%2F2020-09%2Ffn122205_pic_06.jpg&type=IMAGE",
      "provider": "europeana",
      "source_url": "https://www.europeana.eu/item/08604/_filmportal_de_node_1668927?utm_source=api&utm_medium=api&utm_campaign=api2demo",
      "tags": [],
      "title": "Space Dogs",
      "width": null
    },
    {
      "author": "",
      "author_url": null,
      "download_url": "https://www.filmportal.de/sites/default/files/image/2020-09/fn122205_pic_11.jpg",
      "height": null,
      "id": "/08604/_filmportal_de_node_1668923",
      "license": "In Copyright",
      "media_type": "image",
      "preview_url": "https://api.europeana.eu/thumbnail/v2/url.json?uri=https%3A%2F%2Fwww.filmportal.de%2Fsites%2Fdefault%2Ffiles%2Fimage%2F2020-09%2Ffn122205_pic_11.jpg&type=IMAGE",
      "provider": "europeana",
      "source_url": "https://www.europeana.eu/item/08604/_filmportal_de_node_1668923?utm_source=api&utm_medium=api&utm_campaign=api2demo",
      "tags": [],
      "title": "Space Dogs",
      "width": null
    },
    {
      "author": "library of congress, library of congress. science, technology, and business division",
      "author_url": null,
      "download_url": "https://tile.loc.gov/storage-services/service/gdc/gdcwebcasts/17/05/10/st/b1/13/0/170510stb1130/170510stb1130_300.0_thumb.jpg",
      "height": null,
      "id": "http://www.loc.gov/item/2021690527/",
      "license": "Public Domain",
      "media_type": "image",
      "preview_url": "https://tile.loc.gov/storage-services/service/gdc/gdcwebcasts/17/05/10/st/b1/13/0/170510stb1130/170510stb1130_300.0_thumb.jpg",
      "provider": "loc",
      "source_url": "https://www.loc.gov/item/2021690527/",
      "tags": [],
      "title": "Space Ethics: Ethical Implications of Commercial Space Projects",
      "width": null
    },
    {
      "author": "library of congress, library of congress. science, technology, and business division",
      "author_url": null,
      "download_url": "https://tile.loc.gov/storage-services/service/gdc/gdcwebcasts/16/09/29/st/b1/13/0/160929stb1130/160929stb1130_1200.0_thumb.jpg",
      "height": null,
      "id": "http://www.loc.gov/item/2021690308/",
      "license": "Public Domain",
      "media_type": "image",
      "preview_url": "https://tile.loc.gov/storage-services/service/gdc/gdcwebcasts/16/09/29/st/b1/13/0/160929stb1130/160929stb1130_1200.0_thumb.jpg",
      "provider": "loc",
      "source_url": "https://www.loc.gov/item/2021690308/",
      "tags": [],
      "title": "A Space Weather Report: Preparing Space Explorers for Bad Weather",
      "width": null
    },
    {
      "author": "Originalwana",
      "author_url": null,
      "download_url": "https://upload.wikimedia.org/wikipedia/commons/3/3b/Good_Morning_From_the_International_Space_Station.jpg",
      "height": 3280,
      "id": "42268051",
      "license": "CC0",
      "media_type": "image",
      "preview_url": "https://upload.wikimedia.org/wikipedia/commons/thumb/3/3b/Good_Morning_From_the_International_Space_Station.jpg/960px-Good_Morning_From_the_International_Space_Station.jpg",
      "provider": "wikimedia",
      "source_url": "https://commons.wikimedia.org/wiki/File:Good_Morning_From_the_International_Space_Station.jpg",
      "tags": [],
      "title": "Good Morning From the International Space Station",
      "width": 4928
    },
    {
      "author": "Hawky.diddiz",
      "author_url": null,
      "download_url": "https://upload.wikimedia.org/wikipedia/commons/2/2f/Hubble_ultra_deep_field.jpg",
      "height": 3100,
      "id": "1499793",
      "license": "CC0",
      "media_type": "image",
      "preview_url": "https://upload.wikimedia.org/wikipedia/commons/thumb/2/2f/Hubble_ultra_deep_field.jpg/960px-Hubble_ultra_deep_field.jpg",
      "provider": "wikimedia",
      "source_url": "https://commons.wikimedia.org/wiki/File:Hubble_ultra_deep_field.jpg",
      "tags": [],
      "title": "Hubble ultra deep field",
      "width": 3100
    },
    {
      "author": "Tom",
      "author_url": null,
      "download_url": "https://upload.wikimedia.org/wikipedia/commons/7/75/Michael_Gernhardt_in_space_during_STS-69_in_1995.jpg",
      "height": 3000,
      "id": "247187",
      "license": "CC0",
      "media_type": "image",
      "preview_url": "https://upload.wikimedia.org/wikipedia/commons/thumb/7/75/Michael_Gernhardt_in_space_during_STS-69_in_1995.jpg/960px-Michael_Gernhardt_in_space_during_STS-69_in_1995.jpg",
      "provider": "wikimedia",
      "source_url": "https://commons.wikimedia.org/wiki/File:Michael_Gernhardt_in_space_during_STS-69_in_1995.jpg",
      "tags": [],
      "title": "Michael Gernhardt in space during STS-69 in 1995",
      "width": 3011
    },
    {
      "author": "JSC",
      "author_url": null,
      "download_url": "https://images-assets.nasa.gov/image/international-space-station-mockup-training_52233924879_o/international-space-station-mockup-training_52233924879_o~medium.jpg",
      "height": null,
      "id": "international-space-station-mockup-training_52233924879_o",
      "license": "Public Domain",
      "media_type": "image",
      "preview_url": "https://images-assets.nasa.gov/image/international-space-station-mockup-training_52233924879_o/international-space-station-mockup-training_52233924879_o~medium.jpg",
      "provider": "nasa",
      "source_url": "https://images-assets.nasa.gov/image/international-space-station-mockup-training_52233924879_o/collection.json",
      "tags": [
        "Expedition 68",
        "Crew-5"
      ],
      "title": "International Space Station mockup training",
      "width": null
    },
    {
      "author": "JPL",
      "author_url": null,
      "download_url": "https://images-assets.nasa.gov/image/PIA05423/PIA05423~thumb.jpg",
      "height": null,
      "id": "PIA05423",
      "license": "Public Domain",
      "media_type": "image",
      "preview_url": "https://images-assets.nasa.gov/image/PIA05423/PIA05423~thumb.jpg",
      "provider": "nasa",
      "source_url": "https://images-assets.nasa.gov/image/PIA05423/collection.json",
      "tags": [
        "Mimas",
        "Cassini-Huygens"
      ],
      "title": "That No Space Station",
      "width": null
    },
    {
      "author": "JPL",
      "author_url": null,
      "download_url": "https://images-assets.nasa.gov/image/PIA17881/PIA17881~small.jpg",
      "height": null,
      "id": "PIA17881",
      "license": "Public Domain",
      "media_type": "image",
      "preview_url": "https://images-assets.nasa.gov/image/PIA17881/PIA17881~small.jpg",
      "provider": "nasa",
      "source_url": "https://images-assets.nasa.gov/image/PIA17881/collection.json",
      "tags": [
        "Mercury",
        "MESSENGER"
      ],
      "title": "Terror in Space",
      "width": null
    },
    {
      "author": "Carel Visser",
      "author_url": null,
      "download_url": "https://lh4.ggpht.com/YyrjGW8ucfs-_W98kK5q2XX6NcH-3-s_Un_7VhS2JGSlCzob0zkGvFX6oiNVO7Ib0gR1YF-k-IOCz-a8OfEKJeNq-rI=s0",
      "height": 4992,
      "id": "BK-2008-4",
      "license": "CC0",
      "media_type": "image",
      "preview_url": "https://lh4.ggpht.com/YyrjGW8ucfs-_W98kK5q2XX6NcH-3-s_Un_7VhS2JGSlCzob0zkGvFX6oiNVO7Ib0gR1YF-k-IOCz-a8OfEKJeNq-rI=s0",
      "provider": "rijksmuseum",
      "source_url": "http://www.rijksmuseum.nl/en/collection/BK-2008-4",
      "tags": [],
      "title": "Eight Stacked Beams",
      "width": 6666
    },
    {
      "author": "Pieter Jansz Saenredam",
      "author_url": null,
      "download_url": "https://lh3.googleusercontent.com/m_IGl3fefTuaP0r83Yt9yPJR47_LCZfKLlVaMg0jHYwzJCfioMVE5SD8utgPvH_p2SADgqnAprLVEjBueJL8bZznfcp0n6AgCNPwZUPUjA=s0",
      "height": 4157,
      "id": "SK-C-217",
      "license": "CC0",
      "media_type": "image",
      "preview_url": "https://lh3.googleusercontent.com/m_IGl3fefTuaP0r83Yt9yPJR47_LCZfKLlVaMg0jHYwzJCfioMVE5SD8utgPvH_p2SADgqnAprLVEjBueJL8bZznfcp0n6AgCNPwZUPUjA=s0",
      "provider": "rijksmuseum",
      "source_url": "http://www.rijksmuseum.nl/en/collection/SK-C-217",
      "tags": [],
      "title": "Interior of the Sint-Odulphuskerk in Assendelft",
      "width": 6385
    },
    {
      "author": "Constant",
      "author_url": null,
      "download_url": "https://lh5.ggpht.com/nZQ-N5SDXp5FZjDfikKun6qld1jEQxPWc_-ZOOn0Fi4NQB1TtWhl3cJg_9zjyQYRkdAyf6Ab2mfn_kKRripU8ch7rQU=s0",
      "height": 5723,
      "id": "BK-2012-65-1",
      "license": "CC0",
      "media_type": "image",
      "preview_url": "https://lh5.ggpht.com/nZQ-N5SDXp5FZjDfikKun6qld1jEQxPWc_-ZOOn0Fi4NQB1TtWhl3cJg_9zjyQYRkdAyf6Ab2mfn_kKRripU8ch7rQU=s0",
      "provider": "rijksmuseum",
      "source_url": "http://www.rijksmuseum.nl/en/collection/BK-2012-65-1",
      "tags": [],
      "title": "Space Circus",
      "width": 5723
    },
    {
      "author": null,
      "author_url": null,
      "download_url": "https://live.staticflickr.com/65535/54960597244_1139fb4bf6_z.jpg",
      "height": 0,
      "id": "scraped-0",
      "license": "Unknown - Check source",
      "media_type": "image",
      "preview_url": null,
      "provider": "scraper",
      "source_url": "https://www.flickr.com/explore",
      "tags": [],
      "title": "IMG Image 1",
      "width": 0
    },
    {
      "author": null,
      "author_url": null,
      "download_url": "https://live.staticflickr.com/65535/54959718572_08e4e6a496.jpg",
      "height": 0,
      "id": "scraped-1",
      "license": "Unknown - Check source",
      "media_type": "image",
      "preview_url": null,
      "provider": "scraper",
      "source_url": "https://www.flickr.com/explore",
      "tags": [],
      "title": "IMG Image 2",
      "width": 0
    },
    {
      "author": null,
      "author_url": null,
      "download_url": "https://live.staticflickr.com/65535/54959945407_8280432826_w.jpg",
      "height": 0,
      "id": "scraped-2",
      "license": "Unknown - Check source",
      "media_type": "image",
      "preview_url": null,
      "provider": "scraper",
      "source_url": "https://www.flickr.com/explore",
      "tags": [],
      "title": "IMG Image 3",
      "width": 0
    },
    {
      "author": null,
      "author_url": null,
      "download_url": "https://www.nasa.gov/wp-content/themes/nasa/assets/images/nasa-logo@2x.png",
      "height": 0,
      "id": "scraped-0",
      "license": "Unknown - Check source",
      "media_type": "image",
      "preview_url": null,
      "provider": "scraper",
      "source_url": "https://www.nasa.gov/multimedia/imagegallery/",
      "tags": [],
      "title": "IMG NASA Logo",
      "width": 60
    },
    {
      "author": null,
      "author_url": null,
      "download_url": "https://www.nasa.gov/wp-content/themes/nasa/assets/images/nasa-logo@2x.png",
      "height": 0,
      "id": "scraped-1",
      "license": "Unknown - Check source",
      "media_type": "image",
      "preview_url": null,
      "provider": "scraper",
      "source_url": "https://www.nasa.gov/multimedia/imagegallery/",
      "tags": [],
      "title": "IMG NASA Logo",
      "width": 60
    },
    {
      "author": null,
      "author_url": null,
      "download_url": "https://www.nasa.gov/wp-content/uploads/2025/12/1-pia26674-researchers-test-mars-drone-software-in-death-valley-web.jpg?w=1024",
      "height": 576,
      "id": "scraped-2",
      "license": "Unknown - Check source",
      "media_type": "image",
      "preview_url": null,
      "provider": "scraper",
      "source_url": "https://www.nasa.gov/multimedia/imagegallery/",
      "tags": [],
      "title": "IMG Two people stand side by side on a sandy hill, or dune. The person on the left is standing in a blue top, while the person on the right in a gray top is holding a controller. Above and to the left of their heads is a rotorcraft flying above the dune. The background of this image is more sandy dunes.",
      "width": 1024
    }
  ],
  "duration_ms": 5477,
  "media_type": null,
  "provider_errors": [
    {
      "error": "Failed to parse JSON response: error decoding response body",
      "provider": "openverse"
    }
  ],
  "providers_searched": [
    "met",
    "cleveland",
    "picsum",
    "polyhaven",
    "europeana",
    "loc",
    "openverse",
    "wikimedia",
    "nasa",
    "rijksmuseum",
    "scraper:flickr",
    "scraper:nasa-gallery"
  ],
  "query": "space",
  "returned_count": 29,
  "total_count": 902667
}
